pywings/__init__.py
pywings/algo/__init__.py
pywings/ds/__init__.py
pywings-0.0.2.dist-info/LICENSE
pywings-0.0.2.dist-info/METADATA
pywings-0.0.2.dist-info/WHEEL
pywings-0.0.2.dist-info/top_level.txt
pywings-0.0.2.dist-info/RECORD
